CHANGELOG.txt
LICENSE
MANIFEST.in
README.md
pyproject.toml
setup.cfg
setup.py
tox.ini
src/bleach_extras/__init__.py
src/bleach_extras/py.typed
src/bleach_extras/tag_tree_filter.py
src/bleach_extras.egg-info/PKG-INFO
src/bleach_extras.egg-info/SOURCES.txt
src/bleach_extras.egg-info/dependency_links.txt
src/bleach_extras.egg-info/not-zip-safe
src/bleach_extras.egg-info/requires.txt
src/bleach_extras.egg-info/top_level.txt
tests/test_clean.py