Metadata-Version: 2.1
Name: bleach-extras
Version: 0.2.1
Summary: some extensions for bleach
Home-page: http://github.com/jvanasco/bleach_extras
Author: Jonathan Vanasco
Author-email: jonathan@findmeon.com
License: MIT License
Keywords: bleach html-sanitizing
Platform: UNKNOWN
Classifier: License :: OSI Approved :: MIT License
Classifier: Programming Language :: Python
Classifier: Programming Language :: Python :: 3
Classifier: Programming Language :: Python :: 3.6
Classifier: Programming Language :: Python :: 3.7
Classifier: Programming Language :: Python :: 3.8
Classifier: Programming Language :: Python :: 3.9
Classifier: Programming Language :: Python :: 3.10
Classifier: Programming Language :: Python :: 3.11
Classifier: Intended Audience :: Developers
Provides-Extra: testing
